README.md
setup.py
gandb_distributions/__init__.py
gandb_distributions/binomial.py
gandb_distributions/distribution.py
gandb_distributions/gaussian.py
gandb_distributions.egg-info/PKG-INFO
gandb_distributions.egg-info/SOURCES.txt
gandb_distributions.egg-info/dependency_links.txt
gandb_distributions.egg-info/not-zip-safe
gandb_distributions.egg-info/top_level.txt