Metadata-Version: 1.0
Name: gandb-distributions
Version: 1.0
Summary: Gaussian and Binomial distributions
Home-page: UNKNOWN
Author: Max Boguslavskiy
Author-email: UNKNOWN
License: UNKNOWN
Platform: UNKNOWN
